setup.py
src/scripts/trns-remove
src/transmission_helper/__init__.py
src/transmission_helper/remove.py
src/transmission_helper.egg-info/PKG-INFO
src/transmission_helper.egg-info/SOURCES.txt
src/transmission_helper.egg-info/dependency_links.txt
src/transmission_helper.egg-info/top_level.txt