Metadata-Version: 1.0
Name: transmission-helper
Version: 0.4
Summary: Helper scripts for BT Transmission
Home-page: http://www.systemical.com/
Author: Jean-Lou Dupont
Author-email: jl@jldupont.com
License: UNKNOWN
Platform: UNKNOWN
